ihelp/__init__.py
ihelp/helper.py
ihelp-0.0.1.dist-info/LICENSE
ihelp-0.0.1.dist-info/METADATA
ihelp-0.0.1.dist-info/WHEEL
ihelp-0.0.1.dist-info/top_level.txt
ihelp-0.0.1.dist-info/RECORD
