Metadata-Version: 2.1
Name: ihelp
Version: 0.0.1
Summary: run_continuously with schedule
Home-page: https://github.com/coghost/ihelp
Author: lihe
Author-email: imanux@sina.com
License: GPL
Project-URL: Bug Reports, https://github.com/coghost/ihelp/issues
Project-URL: Source, https://github.com/coghost/ihelp
Keywords: ihelp,izen,profig,logzero
Platform: UNKNOWN
Classifier: Programming Language :: Python :: 3.7
Requires-Python: >=3.7
Requires-Dist: psutil
Requires-Dist: wcwidth
Requires-Dist: clint
Requires-Dist: click
Requires-Dist: logzero
